fracability/AbstractClasses.py
fracability/Adapters.py
fracability/Entities.py
fracability/Plotters.py
fracability/Statistics.py
fracability/__init__.py
fracability/examples/__init__.py
fracability/examples/data.py
fracability/examples/datasets/cava_pontrelli/Interpretation_boundary.cpg
fracability/examples/datasets/cava_pontrelli/Interpretation_boundary.dbf
fracability/examples/datasets/cava_pontrelli/Interpretation_boundary.prj
fracability/examples/datasets/cava_pontrelli/Interpretation_boundary.shp
fracability/examples/datasets/cava_pontrelli/Interpretation_boundary.shx
fracability/examples/datasets/cava_pontrelli/Set_a.cpg
fracability/examples/datasets/cava_pontrelli/Set_a.dbf
fracability/examples/datasets/cava_pontrelli/Set_a.prj
fracability/examples/datasets/cava_pontrelli/Set_a.shp
fracability/examples/datasets/cava_pontrelli/Set_a.shx
fracability/examples/datasets/cava_pontrelli/Set_b.cpg
fracability/examples/datasets/cava_pontrelli/Set_b.dbf
fracability/examples/datasets/cava_pontrelli/Set_b.prj
fracability/examples/datasets/cava_pontrelli/Set_b.shp
fracability/examples/datasets/cava_pontrelli/Set_b.shx
fracability/examples/datasets/cava_pontrelli/Set_c.cpg
fracability/examples/datasets/cava_pontrelli/Set_c.dbf
fracability/examples/datasets/cava_pontrelli/Set_c.prj
fracability/examples/datasets/cava_pontrelli/Set_c.shp
fracability/examples/datasets/cava_pontrelli/Set_c.shx
fracability/examples/datasets/cava_pontrelli/output/lengths/Fractures_Length_set1_Pontrelli.csv
fracability/examples/datasets/cava_pontrelli/output/lengths/figures/cens.png
fracability/examples/datasets/cava_pontrelli/output/lengths/figures/no_cens.png
fracability/examples/datasets/cava_pontrelli/output/spacing/Fractures_Spacing_pontrelli.csv
fracability/examples/datasets/cava_pontrelli/output/topology/output_Pontrelli/backbone.cpg
fracability/examples/datasets/cava_pontrelli/output/topology/output_Pontrelli/backbone.dbf
fracability-1.5.4.dist-info/licenses/LICENSE
fracability-1.5.4.dist-info/METADATA
fracability-1.5.4.dist-info/WHEEL
fracability-1.5.4.dist-info/top_level.txt
fracability-1.5.4.dist-info/RECORD
