Metadata-Version: 2.4
Name: FracAbility
Version: 1.5.4
Summary: Analyse fracture networks for digitalized rock outcrops. 
Author-email: Gabriele Benedetti <gabri.benedetti@gmail.com>, Stefano Casiraghi <s.casiraghi21@campus.unimib.it>, Daniela Bertacchi <daniela.bertacchi@unimib.it>, Andrea Bistacchi <andrea.bistacchi@unimib.it>
License: AGPL-3.0 license 
Project-URL: Documentation, https://fracability.readthedocs.io/en/latest/index.html
Project-URL: Bug Tracker, https://github.com/gecos-lab/FracAbility/issues
Project-URL: Source Code, https://github.com/gecos-lab/FracAbility
Keywords: DOM,censoring,fractures,fracture-networks,survival-analysis,reliability
Classifier: Intended Audience :: Science/Research
Classifier: Topic :: Scientific/Engineering :: Information Analysis
Classifier: License :: OSI Approved :: MIT License
Classifier: Operating System :: Microsoft :: Windows
Classifier: Operating System :: POSIX
Classifier: Operating System :: MacOS
Classifier: Programming Language :: Python :: 3.8
Classifier: Programming Language :: Python :: 3.9
Classifier: Programming Language :: Python :: 3.10
Classifier: Programming Language :: Python :: 3.11
Classifier: Programming Language :: Python :: 3.12
Classifier: License :: OSI Approved :: GNU Affero General Public License v3
Requires-Python: >=3.8
License-File: LICENSE
Requires-Dist: pyvista
Requires-Dist: networkx
Requires-Dist: geopandas
Requires-Dist: scipy
Requires-Dist: python-ternary
Requires-Dist: pyperclip
Requires-Dist: pyqt5
Requires-Dist: openpyxl
Requires-Dist: seaborn
Requires-Dist: trame
Requires-Dist: jupyter
Requires-Dist: fiona
Dynamic: license-file
